interactigen/__init__.py
interactigen/commands/__init__.py
interactigen/commands/gen_new_phrasings.py
interactigen/commands/gen_transformed_phrasings.py
interactigen/commons.py
interactigen/interactigen.py
interactigen-0.0.6.dist-info/LICENSE
interactigen-0.0.6.dist-info/METADATA
interactigen-0.0.6.dist-info/WHEEL
interactigen-0.0.6.dist-info/RECORD
