Metadata-Version: 2.1
Name: interactigen
Version: 0.0.6
Summary: Python module for interactional generation.
Home-page: https://github.com/sitinc/interactigen-py
License: MIT
Author: Justin Randall
Author-email: justin@sitinc.net
Requires-Python: >=3.11,<3.13
Classifier: License :: OSI Approved :: MIT License
Classifier: Programming Language :: Python :: 3
Classifier: Programming Language :: Python :: 3.11
Classifier: Programming Language :: Python :: 3.12
Requires-Dist: interacticore (>=0.0.4,<0.0.5)
Requires-Dist: langchain-core (>=0.1.31,<0.2.0)
Project-URL: Documentation, https://github.com/sitinc/interactigen-py
Project-URL: Repository, https://github.com/sitinc/interactigen-py
